Metadata-Version: 1.1
Name: ro-bot
Version: 0.0.1
Summary: Rô bot client
Home-page: https://github.com/brenokcc/robot
Author: Carlos Breno Pereira Silva
Author-email: brenokcc@yahoo.com.br
License: BSD License
Platform: UNKNOWN
Classifier: Environment :: Web Environment
Classifier: Framework :: Django
Classifier: Intended Audience :: Developers
Classifier: License :: OSI Approved :: BSD License
Classifier: Operating System :: OS Independent
Classifier: Programming Language :: Python
Classifier: Topic :: Internet :: WWW/HTTP
Classifier: Topic :: Internet :: WWW/HTTP :: Dynamic Content
